setup.py
ast_probability/Binomialdistribution.py
ast_probability/Gaussiandistribution.py
ast_probability/Generaldistribution.py
ast_probability/__init__.py
ast_probability.egg-info/PKG-INFO
ast_probability.egg-info/SOURCES.txt
ast_probability.egg-info/dependency_links.txt
ast_probability.egg-info/not-zip-safe
ast_probability.egg-info/top_level.txt