Metadata-Version: 1.0
Name: ast-probability
Version: 1.1
Summary: Gaussian and Binomial distributions
Home-page: UNKNOWN
Author: Kyle_1
Author-email: joankorirchemutai@gmail.com
License: UNKNOWN
Platform: UNKNOWN
